arcospy/__init__.py
arcospy/arcospy.py
arcospy-1.3.7.dist-info/LICENSE
arcospy-1.3.7.dist-info/METADATA
arcospy-1.3.7.dist-info/WHEEL
arcospy-1.3.7.dist-info/top_level.txt
arcospy-1.3.7.dist-info/RECORD
