Metadata-Version: 2.1
Name: arcospy
Version: 1.3.7
Summary: Python version of the R arcos package
Home-page: https://github.com/jeffcsauer/arcospy
Author: Python translator: Jeffery Sauer. Original R Package Authors: Washington Post Data Investigations Team
Author-email: jcsauer@terpmail.umd.edu
Classifier: Programming Language :: Python :: 3
Classifier: License :: OSI Approved :: MIT License
Classifier: Operating System :: OS Independent
Requires-Python: >=3.6
License-File: LICENSE
Requires-Dist: pandas
Requires-Dist: requests
